py3tree/__init__.py
py3tree/py3tree.py
py3tree-0.0.3.dist-info/METADATA
py3tree-0.0.3.dist-info/RECORD
py3tree-0.0.3.dist-info/WHEEL
py3tree-0.0.3.dist-info/entry_points.txt
py3tree-0.0.3.dist-info/top_level.txt
