Metadata-Version: 2.1
Name: py3tree
Version: 0.0.3
Summary: Display the i3 tree for the current or all workspaces
Home-page: https://github.com/DavidAntliff/py3tree.git
Author: David Antliff
Author-email: david.antliff@gmail.com
License: UNKNOWN
Keywords: i3 i3ipc
Platform: UNKNOWN
Classifier: Programming Language :: Python
Classifier: Programming Language :: Python :: 2.7
Classifier: Programming Language :: Python :: 3
Classifier: License :: OSI Approved :: GNU General Public License v3 (GPLv3)
Classifier: Environment :: X11 Applications
Classifier: Topic :: Desktop Environment :: Window Managers
Classifier: Operating System :: OS Independent
Requires-Python: >=2.7, !=3.0.*, !=3.1.*, !=3.2.*, !=3.3.*, !=3.4.*, <4
Requires-Dist: future (>=0.16.0)
Requires-Dist: i3ipc (>=1.5.1)
